[
  { "status": 404, "msg": "No such person" },
  { "status": 404, "msg": "No such person" },
  {
    "person": {
      "pets": [
        { "name": "Barney", "kind": "dog", "alive": true },
        { "name": "Shania", "kind": "rock", "alive": false }
      ],
      "username": "tomosim"
    }
  },
  {
    "person": {
      "pets": [{ "name": "Felix", "kind": "cat", "alive": true }],
      "username": "P-Copley"
    }
  },
  {
    "person": {
      "pets": [
        { "name": "Opal", "kind": "cat", "alive": true },
        { "name": "Jeffry", "kind": "cat", "alive": false }
      ],
      "username": "popcorn"
    }
  },
  {
    "person": {
      "pets": [
        { "name": "Elgar", "kind": "pidgeon", "alive": true },
        { "name": "Rodrigo", "kind": "alpaca", "alive": true }
      ],
      "username": "dedekind561"
    }
  },
  {
    "person": {
      "pets": [{ "name": "Henna", "kind": "cat", "alive": false }],
      "username": "RuthYMNg"
    }
  },
  {
    "person": {
      "pets": [
        { "name": "Dave", "kind": "cat", "alive": false },
        { "name": "Pinchy", "kind": "lobster", "alive": false }
      ],
      "username": "rogersop"
    }
  },
  {
    "person": {
      "pets": [
        { "name": "Otis", "kind": "dog", "alive": false },
        { "name": "Branston", "kind": "dog", "alive": true }
      ],
      "username": "icellusedkars"
    }
  },
  {
    "person": {
      "pets": [
        { "name": "Holly", "kind": "hamster", "alive": false },
        { "name": "James Pond", "kind": "goldfish", "alive": false }
      ],
      "username": "MissMallion"
    }
  },
  {
    "person": {
      "pets": [{ "name": "Shnitzel", "kind": "cat", "alive": true }],
      "username": "anatdean"
    }
  },
  {
    "person": {
      "pets": [{ "name": "Karl", "kind": "llama", "alive": true }],
      "username": "ziziou91"
    }
  },
  { "status": 404, "msg": "No such person" }
]
